{"2021-09-05 21:32:43.636769": {"PID": "P125", "Name": "PUMPKIN", "u_Quantity": 2, "Bill_Amount": 80}, "2021-09-05 21:33:33.023032": {"PID": "P107", "Name": "BOURBON", "u_Quantity": 7, "Bill_Amount": 350}, "2021-09-05 21:33:58.232013": {"PID": "P118", "Name": "BUTTER", "u_Quantity": 2, "Bill_Amount": 150}, "2021-09-06 18:47:27.927523": {"PID": "P124", "Name": "POTATO", "u_Quantity": 6, "Bill_Amount": 42}, "2021-09-06 18:47:45.380411": {"PID": "P112", "Name": "7UP", "u_Quantity": 4, "Bill_Amount": 280}, "2021-09-06 18:48:15.258047": {"PID": "P111", "Name": "COLA", "u_Quantity": 3, "Bill_Amount": 225}, "2021-09-06 18:48:36.646132": {"PID": "P108", "Name": "OREO", "u_Quantity": 5, "Bill_Amount": 250}, "2021-09-06 18:49:11.869230": {"PID": "P117", "Name": "CURD", "u_Quantity": 1, "Bill_Amount": 52}, "2021-09-06 18:50:06.600488": {"PID": "P128", "Name": "AVOCADO", "u_Quantity": 3, "Bill_Amount": 105}, "2021-09-06 18:50:35.994246": {"PID": "P104", "Name": "KITKAT", "u_Quantity": 10, "Bill_Amount": 400}}